jardiff/__init__.py
jardiff/__main__.py
jardiff/cli.py
jardiff-0.2.0.dist-info/METADATA
jardiff-0.2.0.dist-info/WHEEL
jardiff-0.2.0.dist-info/entry_points.txt
jardiff-0.2.0.dist-info/licenses/LICENSE
jardiff-0.2.0.dist-info/RECORD
