Metadata-Version: 2.4
Name: jardiff
Version: 0.2.0
Summary: Compare JAR libraries between two directories. Maven-aware, classifier-aware, resilient.
Author: Mohamed Sadok Aounallah
License: MIT License
License-File: LICENSE
Keywords: dependencies,diff,jar,java,maven
Classifier: Environment :: Console
Classifier: Intended Audience :: Developers
Classifier: License :: OSI Approved :: MIT License
Classifier: Programming Language :: Python :: 3
Classifier: Programming Language :: Python :: 3 :: Only
Classifier: Topic :: Software Development :: Build Tools
Requires-Python: >=3.8
